OffSecIta/__init__.py
OffSecIta/corsi.py
OffSecIta/utils.py
offsecita_h4rck4n0-0.1.3.dist-info/METADATA
offsecita_h4rck4n0-0.1.3.dist-info/WHEEL
offsecita_h4rck4n0-0.1.3.dist-info/top_level.txt
offsecita_h4rck4n0-0.1.3.dist-info/RECORD
