Metadata-Version: 2.4
Name: OffSecIta-h4rck4n0
Version: 0.1.3
Summary: Biblioteca per consultare i corsi
Home-page: https://www.youtube.com/@Roby_Kali
Author: h4rck4n0
Dynamic: author
Dynamic: description
Dynamic: description-content-type
Dynamic: home-page
Dynamic: summary
